clientgdocs/README.MD
clientgdocs/__init__.py
clientgdocs/requirements.txt
clientgdocs/thirdparty.json
clientgdocs-0.11.dist-info/LICENSE.rst
clientgdocs-0.11.dist-info/METADATA
clientgdocs-0.11.dist-info/WHEEL
clientgdocs-0.11.dist-info/top_level.txt
clientgdocs-0.11.dist-info/RECORD
