Metadata-Version: 2.1
Name: clientgdocs
Version: 0.11
Summary: Jerrybuilt data exchange through Google Docs - client
Home-page: https://github.com/hansalemaos/clientgdocs
Author: Johannes Fischer
Author-email: aulasparticularesdealemaosp@gmail.com
License: MIT
Keywords: data,exchange
Classifier: Development Status :: 4 - Beta
Classifier: Programming Language :: Python :: 3 :: Only
Classifier: Programming Language :: Python :: 3.10
Classifier: Topic :: Software Development :: Libraries :: Python Modules
Classifier: Topic :: Utilities
License-File: LICENSE.rst
Requires-Dist: beautifulsoup4
Requires-Dist: flatten-any-dict-iterable-or-whatsoever
Requires-Dist: lxml
Requires-Dist: passprotecttxt
Requires-Dist: pfehler
Requires-Dist: requests
